popro/__init__.py
popro/cli.py
popro/engine_template.py
popro/popro.py
popro/engines/__init__.py
popro/engines/tceduca.py
popro-0.1.1.dist-info/AUTHORS.rst
popro-0.1.1.dist-info/LICENSE
popro-0.1.1.dist-info/METADATA
popro-0.1.1.dist-info/WHEEL
popro-0.1.1.dist-info/entry_points.txt
popro-0.1.1.dist-info/top_level.txt
popro-0.1.1.dist-info/RECORD
