Metadata-Version: 2.1
Name: popro
Version: 0.1.1
Summary: A population projection engine
Home-page: https://github.com/aiboxlab-pne/popro
Author: derycck
Author-email: derycck@gmail.com
License: MIT license
Keywords: popro
Classifier: Development Status :: 2 - Pre-Alpha
Classifier: Intended Audience :: Developers
Classifier: License :: OSI Approved :: MIT License
Classifier: Natural Language :: English
Classifier: Programming Language :: Python :: 3
Classifier: Programming Language :: Python :: 3.6
Classifier: Programming Language :: Python :: 3.7
Classifier: Programming Language :: Python :: 3.8
Requires-Python: >=3.6
License-File: LICENSE
License-File: AUTHORS.rst
Requires-Dist: Click (>=7.0)
Requires-Dist: pandas (>=1.4)
